{
  "Vaccines": [
    {
      "Id": "PCR",
      "Name": "კოვიდ 19 ვაქცინაცია (AstraZeneca)",
      "Description": "5 მაისიდან 20.00 სთ-დან იწყება ასტრაზენეკას მე-2 დოზაზე რეგისტრაცია. აცრის ჩატარება შესაძლებელი იქნება 10 მაისიდან. თქვენ შეგიძლიათ დარეგისტრირდეთ მე-2 დოზის მისაღებად ნებისმიერ დაწესებულებაში პირველი აცრიდან 4 - 12 კვირის ინტერვალში. ასაკობრივი შეზღუდვა არ ვრცელდება მათზე, ვინც პირველი დოზით აცრა ჩაიტარა ასტრაზენეკას ვაქცინით.\nდამატებითი ფანჯრები ეტაპობრივად გაიხსნება",
      "Municipalities": [
        {
          "RegionId": "31520d88-870e-485e-a833-5ca9e20e84fa",
          "RegionName": "აჭარა",
          "Id": "057b6a5e-e0ae-41ed-99e5-a425a367f69b",
          "Name": "ბათუმი",
          "Locations": [
            {
              "BranchId": "1cc40657-dcdd-44fa-8f75-4f1a183febce",
              "BranchName": "შპს \"ბათუმის სამედიცინო ცენტრი\"",
              "AvailableCount": 536,
              "BranchAddress": "ბათუმი, კახაბერის ქ. N36"
            },
            {
              "BranchId": "26e2ab50-ed88-40b1-9b40-6d1d810dd958",
              "BranchName": "შპს მაღალტექნოლოგიური ჰოსპიტალი მედცენტრი",
              "AvailableCount": 395,
              "BranchAddress": "ქ.ბათუმი, პუშკინის ქ.N118/120"
            }
          ],
          "AvailableCount": 931
        },
        {
          "RegionId": "31520d88-870e-485e-a833-5ca9e20e84fa",
          "RegionName": "აჭარა",
          "Id": "c643f7bc-2888-4053-81b6-79855216294f",
          "Name": "ქობულეთი",
          "Locations": [
            {
              "BranchId": "926f288e-95c5-43cd-ad10-24263212f0aa",
              "BranchName": "სს \"ევექსის ჰოსპიტლები\"  – ქობულეთის ჰოსპიტალი",
              "AvailableCount": 112,
              "BranchAddress": "აბაშიძის ქ N18, მიმდებარედ"
            }
          ],
          "AvailableCount": 112
        },
        {
          "RegionId": "27428de4-bb76-47f2-bfac-26700623a05d",
          "RegionName": "გურია",
          "Id": "730cfadd-1b98-43ee-a908-81942b384b8b",
          "Name": "ოზურგეთი",
          "Locations": [
            {
              "BranchId": "b14d6cb5-9f46-4f80-a0a2-18ca4a282625",
              "BranchName": "შპს მედალფა_ოზურგეთი",
              "AvailableCount": 379,
              "BranchAddress": "ოზურგეთი, ე. ნინოშვილის ქ. №3 (იყო ჟღენტის ქ. №4) (თბილისი, ჯ. ბაგრატიონის ქ. №6ა)"
            }
          ],
          "AvailableCount": 379
        },
        {
          "RegionId": "5d129a50-30e9-4b10-8d4d-3febb32ec32c",
          "RegionName": "თბილისი",
          "Id": "e937c51e-2ed5-414e-b406-b9b1c59c6e29",
          "Name": "დიდუბე",
          "Locations": [
            {
              "BranchId": "d498c105-2c24-4217-8143-17ba88d01c39",
              "BranchName": "სს „ევექსის ჰოსპიტლები“ - მ. იაშვილის სახელობის ბავშვთა ცენტრალური საავადმყოფო",
              "AvailableCount": 824,
              "BranchAddress": "თბილისი, ლუბლიანას ქ. 13/მიხეილ ჭიაურელის ქ. 6 (ყოფ.: ლუბლიანას ქ. 2/6)"
            },
            {
              "BranchId": "89e3d6ec-fbe1-4673-95e1-74203d7f38e4",
              "BranchName": "შპს აკადემიკოს ო. ღუდუშაურის სახელობის ეროვნული სამედიცინო ცენტრი",
              "AvailableCount": 126,
              "BranchAddress": "თბილისი,ნოდარ ბოხუას ქ.N12/ლუბლიანას ქ.N66"
            },
            {
              "BranchId": "9f433fbf-df54-4d7d-a8df-2d653a249ee7",
              "BranchName": "ა(ა)იპ \"ნიუ ვიჟენ საუნივერსიტეტო ჰოსპიტალი\"",
              "AvailableCount": 370,
              "BranchAddress": "თბილისი, ლუბლიანას ქუჩა N13 / მიხეილ ჭიაურელის ქუჩა N6"
            }
          ],
          "AvailableCount": 1320
        },
        {
          "RegionId": "5d129a50-30e9-4b10-8d4d-3febb32ec32c",
          "RegionName": "თბილისი",
          "Id": "3bf56eb3-120d-41f3-adfb-57f4e8b6acf0",
          "Name": "ვაკე",
          "Locations": [
            {
              "BranchId": "e16014e2-ea3f-41a8-a277-6f2bcfc33901",
              "BranchName": "შპს ს. ხეჩინაშვილის სახელობის საუნივერსიტეტო კლინიკა",
              "AvailableCount": 1120,
              "BranchAddress": "თბილისი, ი. ჭავჭავაძის გამზირი №33"
            }
          ],
          "AvailableCount": 1120
        },
        {
          "RegionId": "5d129a50-30e9-4b10-8d4d-3febb32ec32c",
          "RegionName": "თბილისი",
          "Id": "d02b650d-95c9-453b-a881-866b90b72562",
          "Name": "ისანი",
          "Locations": [
            {
              "BranchId": "d043e1d0-4acb-495b-82c3-d9cdc923e588",
              "BranchName": "შპს თბილისის სახელმწიფო სამედიცინო უნივერსიტეტისა და ინგოროყვას მაღალი სამედიცინო ტექნოლოგიების საუნივერსიტეტო კლინიკა",
              "AvailableCount": 3,
              "BranchAddress": "თბილისი, წინანდლის ქ. #9"
            }
          ],
          "AvailableCount": 3
        },
        {
          "RegionId": "5d129a50-30e9-4b10-8d4d-3febb32ec32c",
          "RegionName": "თბილისი",
          "Id": "bdaa7aaf-4393-421a-8f33-81da384ad44b",
          "Name": "კრწანისი",
          "Locations": [
            {
              "BranchId": "f16c1454-b779-4057-a4eb-e173166acf5a",
              "BranchName": "შპს ნიუ ჰოსპიტალს",
              "AvailableCount": 716,
              "BranchAddress": "თბილისი, გორგასლის/კრწანისის ქ, N 71/12 (თბილისი, აღმაშენებლის 148/111)"
            }
          ],
          "AvailableCount": 716
        },
        {
          "RegionId": "5d129a50-30e9-4b10-8d4d-3febb32ec32c",
          "RegionName": "თბილისი",
          "Id": "e497ed35-b34f-417c-b7a6-4f8c13a588d1",
          "Name": "საბურთალო",
          "Locations": [
            {
              "BranchId": "2301128f-af85-450d-b180-b0eca0a21095",
              "BranchName": "შპს აკადემიკოს ნიკოლოზ ყიფშიძის სახელობის ცენტრალური საუნივერსიტეტო კლინიკა",
              "AvailableCount": 8970,
              "BranchAddress": "ქ. თბილისი, ვაჟა-ფშაველას  №29"
            },
            {
              "BranchId": "8486a9e6-18aa-41ea-a2a7-269061b8cd11",
              "BranchName": "შპს აკადემიკოს ვახტანგ ბოჭორიშვილის კლინიკა.",
              "AvailableCount": 361,
              "BranchAddress": "თბილისი, ალ. ყაზბეგის გამზირი N16"
            },
            {
              "BranchId": "b3484c29-b0d6-440b-8c91-e8ffcc12cd83",
              "BranchName": "სს ინფექციური პათოლოგიის შიდსისა და კლინიკური იმუნოლოგიის სამეცნიერო-პრაქტიკული ცენტრი",
              "AvailableCount": 738,
              "BranchAddress": "თბილისი, ყაზბეგის №16"
            }
          ],
          "AvailableCount": 10069
        },
        {
          "RegionId": "09c1e04c-c664-4252-a30a-2a71ba72c2e2",
          "RegionName": "იმერეთი",
          "Id": "f94b943e-a45a-4f51-8abc-479ba287be2f",
          "Name": "ბაღდათი",
          "Locations": [
            {
              "BranchId": "c8b86b01-7cd8-43b9-83cd-3eb75b183848",
              "BranchName": "შპს „ჯეო ჰოსპიტალს\" - ბაღდათის მრავალპროფილური სამედიცინო ცენტრი",
              "AvailableCount": 956,
              "BranchAddress": "ბაღდათი,\tკახიანის №84 (თბილისი კოსტავას 67, ბინა 71)"
            }
          ],
          "AvailableCount": 956
        },
        {
          "RegionId": "09c1e04c-c664-4252-a30a-2a71ba72c2e2",
          "RegionName": "იმერეთი",
          "Id": "02673bd8-902d-4a68-bff4-7a3eacc074e5",
          "Name": "საჩხერე",
          "Locations": [
            {
              "BranchId": "b4e96afd-2465-44dc-a1b4-5f3f0b26d51b",
              "BranchName": "სს საჩხერის რაიონული საავადმყოფო-პოლიკლინიკური გაერთიანება",
              "AvailableCount": 560,
              "BranchAddress": "ივ. გომართელის ქ. #17"
            }
          ],
          "AvailableCount": 560
        },
        {
          "RegionId": "09c1e04c-c664-4252-a30a-2a71ba72c2e2",
          "RegionName": "იმერეთი",
          "Id": "8e18ed10-f27d-4fb9-9baa-7e00d5289aeb",
          "Name": "ქუთაისი",
          "Locations": [
            {
              "BranchId": "cc24c650-2e60-41c8-acfa-48795793b309",
              "BranchName": "თანამედროვე სამედიცინო ტექნოლოგიების დასავლეთის რეგიონალური ცენტრი",
              "AvailableCount": 1478,
              "BranchAddress": "ქ.ქუთაისი,ფოთის ქუჩა N40"
            }
          ],
          "AvailableCount": 1478
        },
        {
          "RegionId": "09c1e04c-c664-4252-a30a-2a71ba72c2e2",
          "RegionName": "იმერეთი",
          "Id": "e75b3390-365a-4499-9aa9-c08bf7bd8fcc",
          "Name": "ჭიათურა",
          "Locations": [
            {
              "BranchId": "51b0a599-8d50-4530-8441-4bebefd4e460",
              "BranchName": "შპს „ჯეო ჰოსპიტალს\" - ჭიათურის ამბულატორული ცენტრი",
              "AvailableCount": 920,
              "BranchAddress": "ჭიათურა, აღმაშენებლის ქ N14"
            }
          ],
          "AvailableCount": 920
        },
        {
          "RegionId": "d1e285b5-5b60-42c6-9bc2-ac7646a9c96a",
          "RegionName": "კახეთი",
          "Id": "e77963c8-7b89-4662-8b70-92741c849e69",
          "Name": "გურჯაანი",
          "Locations": [
            {
              "BranchId": "d0376b52-af3e-44a7-ba20-208df006c981",
              "BranchName": "შპს „ჯეო ჰოსპიტალს\" - გურჯაანის მრავალპროფილური სამედიცინო ცენტრი",
              "AvailableCount": 192,
              "BranchAddress": "გურჯაანი, მარჯანიშვილის ქ. №35(იყო გურჯაანი, დ. აღმაშენებლის №144 (თბილისი კოსტავას 67, ბინა 71)"
            }
          ],
          "AvailableCount": 192
        },
        {
          "RegionId": "d1e285b5-5b60-42c6-9bc2-ac7646a9c96a",
          "RegionName": "კახეთი",
          "Id": "c82238fa-d37f-40f6-a3ad-1da0683e0da7",
          "Name": "თელავი",
          "Locations": [
            {
              "BranchId": "a8065ff8-031e-41dc-8b8d-8c325e5c9af4",
              "BranchName": "სს „ევექსი ჰოსპიტალები“ - თელავის რეფერალური ჰოსპიტალი",
              "AvailableCount": 349,
              "BranchAddress": "სეხნიაშვილის ქ. №1"
            }
          ],
          "AvailableCount": 349
        },
        {
          "RegionId": "d1e285b5-5b60-42c6-9bc2-ac7646a9c96a",
          "RegionName": "კახეთი",
          "Id": "c50ea368-28b3-498f-9c01-0278bb54680d",
          "Name": "ლაგოდეხი",
          "Locations": [
            {
              "BranchId": "a3d354de-0c75-4353-81b2-e2d7a5e5acc6",
              "BranchName": "შპს \"არქიმედეს კლინიკა\" ლაგოდეხი 9 აპრილი",
              "AvailableCount": 173,
              "BranchAddress": "ლაგოდეხი, 9 აპრილის ქუჩა (თბილისი, ალ. ყაზბეგის №34)"
            }
          ],
          "AvailableCount": 173
        },
        {
          "RegionId": "b5a01ce4-bbfc-4b7e-a519-ba11dd7146bb",
          "RegionName": "მცხეთა-მთიანეთი",
          "Id": "32f910b4-32be-4ee3-bde2-687f5c09db58",
          "Name": "დუშეთი",
          "Locations": [
            {
              "BranchId": "31f728e7-e6c2-487a-8068-6123d9f657ae",
              "BranchName": "შპს „ჯეო ჰოსპიტალს\" - დუშეთის მრავალპროფილური სამედიცინო ცენტრი",
              "AvailableCount": 319,
              "BranchAddress": "დუშეთი,\tსტალინის ქ. №71 (თბილისი კოსტავას 67, ბინა 71)"
            }
          ],
          "AvailableCount": 319
        },
        {
          "RegionId": "b5a01ce4-bbfc-4b7e-a519-ba11dd7146bb",
          "RegionName": "მცხეთა-მთიანეთი",
          "Id": "c7ac1b81-8750-490c-82ba-febce850ebf8",
          "Name": "მცხეთა",
          "Locations": [
            {
              "BranchId": "ecd911d6-cd3d-4713-adbb-666a973a8111",
              "BranchName": "შპს ,, მცხეთის სამედიცინო ცენტრი\"",
              "AvailableCount": 468,
              "BranchAddress": "ქ. მცხეთა, სამხედროს ქ. N20"
            }
          ],
          "AvailableCount": 468
        },
        {
          "RegionId": "6d893d1f-3851-4d80-b7fc-020179c8a4c0",
          "RegionName": "რაჭა-ლეჩხუმი და ქვემო სვანეთი",
          "Id": "5aea027a-1970-4262-9c8b-85d804d049a2",
          "Name": "ამბროლაური",
          "Locations": [
            {
              "BranchId": "838c60c2-a8fe-4633-8aa1-28a7dde7afe1",
              "BranchName": "შპს \"რეგიონული ჯანდაცვის ცენტრი\"-ამბროლაური",
              "AvailableCount": 324,
              "BranchAddress": "ბრატისლავა-რაჭის11"
            }
          ],
          "AvailableCount": 324
        },
        {
          "RegionId": "a2a56af7-2f62-4ffa-aa56-038328bd5b32",
          "RegionName": "სამეგრელო და ზემო სვანეთი",
          "Id": "f736a3b3-c9cb-46b0-b18f-ee5627f6122a",
          "Name": "ზუგდიდი",
          "Locations": [
            {
              "BranchId": "54c76614-d1b1-47c1-9c12-f0415d1ac17c",
              "BranchName": "ნიკოლოზ ყიფშიძის სახელობის ცენტრალური საუნივერსიტეტო კლინიკა, ზუგდიდის რაიონი სოფელი რუხი",
              "AvailableCount": 167,
              "BranchAddress": "ზუგდიდი, სოფელი რუხი"
            },
            {
              "BranchId": "480edfc8-b97e-4db1-b4b7-262d35b63235",
              "BranchName": "სს \"ევექსის ჰოსპიტლები\" - ზუგდიდის რეფერალური ჰოსპიტალი",
              "AvailableCount": 359,
              "BranchAddress": "ზუგდიდი, გამსახურდიას ქ. # 206"
            }
          ],
          "AvailableCount": 526
        },
        {
          "RegionId": "acecd83d-fb22-44f9-b69d-3333aceb79a6",
          "RegionName": "სამცხე-ჯავახეთი",
          "Id": "c57a9137-d6bb-4247-a012-5e9b51558c89",
          "Name": "ახალქალაქი",
          "Locations": [
            {
              "BranchId": "869212c2-344d-45a3-8b53-311112b62839",
              "BranchName": "სს \"ევექსის ჰოსპიტლები\"  – ახალქალაქის ჰოსპიტალი",
              "AvailableCount": 377,
              "BranchAddress": "დ. აღმაშენებლის ქ N 31"
            }
          ],
          "AvailableCount": 377
        },
        {
          "RegionId": "acecd83d-fb22-44f9-b69d-3333aceb79a6",
          "RegionName": "სამცხე-ჯავახეთი",
          "Id": "b1cddc96-b0c0-49cf-b38e-0a8c40512e50",
          "Name": "ახალციხე",
          "Locations": [
            {
              "BranchId": "f29ad9b3-018f-4db9-b8d0-d4f7d7a596aa",
              "BranchName": "სს \"ევექსის ჰოსპიტლები\"  – ახალციხის რეფერალური ჰოსპიტალი",
              "AvailableCount": 183,
              "BranchAddress": "რუსთაველის ქ N105ა"
            }
          ],
          "AvailableCount": 183
        },
        {
          "RegionId": "f2cf4fc9-7037-4c56-8db7-bd9a6ddadd8a",
          "RegionName": "ქვემო ქართლი",
          "Id": "98a421a5-14d8-4cdd-bc99-5f70575c15ab",
          "Name": "გარდაბანი",
          "Locations": [
            {
              "BranchId": "71928d68-b24b-421d-9c44-69afacb65da8",
              "BranchName": "შპს „ჯეო ჰოსპიტალს\" - გარდაბნის მრავალპროფილური სამედიცინო ცენტრი",
              "AvailableCount": 346,
              "BranchAddress": "ქ. გარდაბანი, ლესელიძის ქ. N1(იყო დ.აღმაშენებლის №27 (თბილისი კოსტავას 67, ბინა 71)"
            }
          ],
          "AvailableCount": 346
        },
        {
          "RegionId": "f2cf4fc9-7037-4c56-8db7-bd9a6ddadd8a",
          "RegionName": "ქვემო ქართლი",
          "Id": "b1fc28da-619f-433d-bd7f-5614381ad7d0",
          "Name": "მარნეული",
          "Locations": [
            {
              "BranchId": "ead671d0-a27e-48cd-8abb-90e2ce5d04f4",
              "BranchName": "შპს „ჯეო ჰოსპიტალს\" - მარნეულის მრავალპროფილური სამედიცინო ცენტრი",
              "AvailableCount": 286,
              "BranchAddress": "მარნეული, ყოფილი სამხედრო ქალაქის ტერიტორია"
            }
          ],
          "AvailableCount": 286
        },
        {
          "RegionId": "f2cf4fc9-7037-4c56-8db7-bd9a6ddadd8a",
          "RegionName": "ქვემო ქართლი",
          "Id": "b5163e68-53b7-4585-81b1-b27e10a96e46",
          "Name": "რუსთავი",
          "Locations": [
            {
              "BranchId": "b9524103-a897-43f3-a983-876b78d5d26f",
              "BranchName": "შპს \"კლინიკა რუსთავი\"",
              "AvailableCount": 689,
              "BranchAddress": "რუსთავი, VII მ/რ"
            }
          ],
          "AvailableCount": 689
        },
        {
          "RegionId": "ae3b6e33-6cd7-4b24-bf74-865cfabc2839",
          "RegionName": "შიდა ქართლი",
          "Id": "4561b508-0a64-4f59-b0f6-bf14e3e02fa4",
          "Name": "გორი",
          "Locations": [
            {
              "BranchId": "70ff295b-df28-4b41-a0d5-00a35e4b4762",
              "BranchName": "შპს გორმედი",
              "AvailableCount": 350,
              "BranchAddress": "გორი, ცხინვალის გზატკეცილი №14"
            },
            {
              "BranchId": "46843c12-6e0f-4d11-bca5-cfcad0d5edf8",
              "BranchName": "სსიპ გიორგი აბრამიშვილის სახელობის საქართველოს თავდაცვის სამინისტროს სამხედრო ჰოსპიტალი",
              "AvailableCount": 26,
              "BranchAddress": "გორი. ჭავჭავაძის N56"
            }
          ],
          "AvailableCount": 376
        },
        {
          "RegionId": "ae3b6e33-6cd7-4b24-bf74-865cfabc2839",
          "RegionName": "შიდა ქართლი",
          "Id": "5f90debb-124e-402f-bb66-6ec32d3b4c82",
          "Name": "ხაშური",
          "Locations": [
            {
              "BranchId": "9c661cfd-27aa-4381-911c-8338afece88f",
              "BranchName": "შპს \"ახალი კლინიკა\"",
              "AvailableCount": 250,
              "BranchAddress": "ხაშური, რუსთაველის ქ.N40."
            }
          ],
          "AvailableCount": 250
        }
      ],
      "AvailableCount": 23422
    },
    {
      "Id": "CovidPfizer ",
      "Name": "კოვიდ 19 ვაქცინაცია (Pfizer)",
      "Description": "21 აპრილიდან თქვენ შეგიძლიათ დაჯავშნოთ ადგილი ფაიზერის მე-2 დოზის მისაღებად, რისთვისაც უნდა გქონდეთ ჩატარებული 1 დოზით აცრა.\nაუცილებელია, რომ ჯავშანი გააკეთოთ იმავე კლინიკაში სადაც ჩაიატარეთ პირველი აცრა.\nაუცილებელია, რომ ჯავშანი გააკეთოთ 21-30 დღიან შუალედში პირველი აცრიდან და არ ჩაეწეროთ 20 დღიან ინტერვალის გასვლამდე.\nგთხოვთ შეინახეთ ჯავშნის კოდი, ვინაიდან ის დაგჭირდებათ უახლოეს მომავალაში კოვიდ პასპორტის მობილური აპლიკაციის გასააქტიურებლად\n",
      "Municipalities": [
        {
          "RegionId": "31520d88-870e-485e-a833-5ca9e20e84fa",
          "RegionName": "აჭარა",
          "Id": "057b6a5e-e0ae-41ed-99e5-a425a367f69b",
          "Name": "ბათუმი",
          "Locations": [
            {
              "BranchId": "0381b222-2f74-45de-8a62-5d5f522db2d8",
              "BranchName": "შპს ბათუმის რესპუბლიკური კლინიკური საავადმყოფო",
              "AvailableCount": 459,
              "BranchAddress": "ტბელ აბუსერიძის ქუჩა  N2/პუშკინის ქუჩა N164"
            }
          ],
          "AvailableCount": 459
        },
        {
          "RegionId": "5d129a50-30e9-4b10-8d4d-3febb32ec32c",
          "RegionName": "თბილისი",
          "Id": "d02b650d-95c9-453b-a881-866b90b72562",
          "Name": "ისანი",
          "Locations": [
            {
              "BranchId": "709cac8b-100d-4ec0-824d-b663c93257c5",
              "BranchName": "შპს \"ამტელ ჰოსპიტალ პირველი კლინიკური\"",
              "AvailableCount": 290,
              "BranchAddress": "თბილისი, წინანდლის ქ. №9"
            }
          ],
          "AvailableCount": 290
        },
        {
          "RegionId": "5d129a50-30e9-4b10-8d4d-3febb32ec32c",
          "RegionName": "თბილისი",
          "Id": "e497ed35-b34f-417c-b7a6-4f8c13a588d1",
          "Name": "საბურთალო",
          "Locations": [
            {
              "BranchId": "2301128f-af85-450d-b180-b0eca0a21095",
              "BranchName": "შპს აკადემიკოს ნიკოლოზ ყიფშიძის სახელობის ცენტრალური საუნივერსიტეტო კლინიკა",
              "AvailableCount": 283,
              "BranchAddress": "ქ. თბილისი, ვაჟა-ფშაველას  №29"
            },
            {
              "BranchId": "6cc8d6c2-2b20-4c4b-8a2c-e93e40adec6a",
              "BranchName": "შპს კავკასიის მედიცინის ცენტრი",
              "AvailableCount": 298,
              "BranchAddress": "თბილისი, ქავთარაძის ქ. №23"
            }
          ],
          "AvailableCount": 581
        },
        {
          "RegionId": "5d129a50-30e9-4b10-8d4d-3febb32ec32c",
          "RegionName": "თბილისი",
          "Id": "a9503a34-cf58-4421-816c-556d0ab88a38",
          "Name": "სამგორი",
          "Locations": [
            {
              "BranchId": "379abb1b-d4ad-4f2c-a343-2bb702d88a00",
              "BranchName": "სს „ევექსის ჰოსპიტლები“ - ივ. ბოკერიას სახელობის ჰოსპიტალი",
              "AvailableCount": 270,
              "BranchAddress": "ქინძმარაულის I შესახვევი, №1-ში"
            }
          ],
          "AvailableCount": 270
        },
        {
          "RegionId": "09c1e04c-c664-4252-a30a-2a71ba72c2e2",
          "RegionName": "იმერეთი",
          "Id": "8e18ed10-f27d-4fb9-9baa-7e00d5289aeb",
          "Name": "ქუთაისი",
          "Locations": [
            {
              "BranchId": "4d06171c-2256-4283-8e87-f7d741d73775",
              "BranchName": "შპს \"დასავლეთ საქართველოს სამედიცინო ცენტრი\"",
              "AvailableCount": 471,
              "BranchAddress": "ჯავახიშვილის ქ.N83ა"
            }
          ],
          "AvailableCount": 471
        }
      ],
      "AvailableCount": 2071
    },
    {
      "Id": "Sinopharm",
      "Name": "კოვიდ 19 ვაქცინაცია (Sinopharm)",
      "Description": null,
      "Municipalities": [
        {
          "RegionId": "31520d88-870e-485e-a833-5ca9e20e84fa",
          "RegionName": "აჭარა",
          "Id": "10ec6613-1f66-4a9a-b48c-c69a7b392eed",
          "Name": "ხულო",
          "Locations": [
            {
              "BranchId": "d676bd9f-4ed5-4000-8a6d-9c7b179618ea",
              "BranchName": "სს \"ევექსის კლინიკები\"-ხულოს კლინიკა",
              "AvailableCount": 117,
              "BranchAddress": "აღმაშენებლის ქ.N1"
            }
          ],
          "AvailableCount": 117
        },
        {
          "RegionId": "b5a01ce4-bbfc-4b7e-a519-ba11dd7146bb",
          "RegionName": "მცხეთა-მთიანეთი",
          "Id": "c7ac1b81-8750-490c-82ba-febce850ebf8",
          "Name": "მცხეთა",
          "Locations": [
            {
              "BranchId": "78d3bd9f-0cbf-4cc1-8b0c-9429712c6990",
              "BranchName": "შპს \"მცხეთის პირველადი  ჯანდაცვის ცენტრი ჯანმრთელი თაობა\"",
              "AvailableCount": 1,
              "BranchAddress": "მცხეთა, კოსტავას ქ.№28"
            }
          ],
          "AvailableCount": 1
        },
        {
          "RegionId": "6d893d1f-3851-4d80-b7fc-020179c8a4c0",
          "RegionName": "რაჭა-ლეჩხუმი და ქვემო სვანეთი",
          "Id": "8ebf0df0-4d52-4779-b8cb-f3ac6a2a4a26",
          "Name": "ლენტეხი",
          "Locations": [
            {
              "BranchId": "27a0caa0-f03c-49a6-b6aa-d209bdb405d1",
              "BranchName": "შპს რეგიონული ჯანდაცვის ცენტრი-ლენტეხი",
              "AvailableCount": 92,
              "BranchAddress": "ლენტეხი, დავით აღმაშენებლის ქ N1"
            }
          ],
          "AvailableCount": 92
        },
        {
          "RegionId": "6d893d1f-3851-4d80-b7fc-020179c8a4c0",
          "RegionName": "რაჭა-ლეჩხუმი და ქვემო სვანეთი",
          "Id": "428c09d6-3c94-4122-93ac-d9717a559b25",
          "Name": "ცაგერი",
          "Locations": [
            {
              "BranchId": "45894a13-ed11-4b4e-9d4b-f6e8e1810589",
              "BranchName": "შპს რეგიონული ჯანდაცვის ცენტრი ცაგერი",
              "AvailableCount": 1,
              "BranchAddress": "ცაგერი, რუსთაველის ქ N31"
            }
          ],
          "AvailableCount": 1
        },
        {
          "RegionId": "a2a56af7-2f62-4ffa-aa56-038328bd5b32",
          "RegionName": "სამეგრელო და ზემო სვანეთი",
          "Id": "fd0dbb0f-4eb4-457a-8ee6-aebcbc200290",
          "Name": "მესტია",
          "Locations": [
            {
              "BranchId": "5e9f74c3-7965-45a0-b4e9-f54c01c95c51",
              "BranchName": "შპს \"მესტიის საავადმყოფო-ამბულატორიული გაერთიანება\".",
              "AvailableCount": 138,
              "BranchAddress": "მესტია, ი.გაბლიანის ქ.N13."
            }
          ],
          "AvailableCount": 138
        },
        {
          "RegionId": "a2a56af7-2f62-4ffa-aa56-038328bd5b32",
          "RegionName": "სამეგრელო და ზემო სვანეთი",
          "Id": "a7cbd852-3a6a-421c-ab7c-125d5a0c1389",
          "Name": "ჩხოროწყუ",
          "Locations": [
            {
              "BranchId": "4322fc5c-9b50-430f-ab09-56866bf74579",
              "BranchName": "სს \"ევექსის კლინიკები\"-ჩხოროწყუს კლინიკა",
              "AvailableCount": 113,
              "BranchAddress": "ჩხოროწყუ,აღმაშენებლის ქ.N19"
            }
          ],
          "AvailableCount": 113
        },
        {
          "RegionId": "a2a56af7-2f62-4ffa-aa56-038328bd5b32",
          "RegionName": "სამეგრელო და ზემო სვანეთი",
          "Id": "30a4fdaa-03a8-4de4-aa7b-eda126e60136",
          "Name": "წალენჯიხა",
          "Locations": [
            {
              "BranchId": "b553411a-7732-4fc2-a78c-fe2e54d1f1cc",
              "BranchName": "სს,, ევექსის კლინიკები'წალენჯიხისს კლინიკა",
              "AvailableCount": 150,
              "BranchAddress": "ჭურღულიას ქ N6"
            }
          ],
          "AvailableCount": 150
        },
        {
          "RegionId": "acecd83d-fb22-44f9-b69d-3333aceb79a6",
          "RegionName": "სამცხე-ჯავახეთი",
          "Id": "1eeed714-6387-43f1-82a4-43ec890db185",
          "Name": "ადიგენი",
          "Locations": [
            {
              "BranchId": "5e4bc35a-c360-4a1c-a84d-ef4815a04c1e",
              "BranchName": "სს\"ევექსის კლინიკები\"-ადიგენის კლინიკა",
              "AvailableCount": 78,
              "BranchAddress": "დაბა ადიგენი,ბალახაშვილის ქ N11"
            }
          ],
          "AvailableCount": 78
        },
        {
          "RegionId": "acecd83d-fb22-44f9-b69d-3333aceb79a6",
          "RegionName": "სამცხე-ჯავახეთი",
          "Id": "cb95dc4c-e40a-4a36-b7e5-6d7813903c67",
          "Name": "ასპინძა",
          "Locations": [
            {
              "BranchId": "8b63a2ff-bb83-4e5b-9a87-22698e2aa3e4",
              "BranchName": "სს\"ევექსის კლინიკები\"-ასპინძის კლინიკა",
              "AvailableCount": 39,
              "BranchAddress": "დაბა ასპინძა"
            }
          ],
          "AvailableCount": 39
        },
        {
          "RegionId": "acecd83d-fb22-44f9-b69d-3333aceb79a6",
          "RegionName": "სამცხე-ჯავახეთი",
          "Id": "c57a9137-d6bb-4247-a012-5e9b51558c89",
          "Name": "ახალქალაქი",
          "Locations": [
            {
              "BranchId": "869212c2-344d-45a3-8b53-311112b62839",
              "BranchName": "სს \"ევექსის ჰოსპიტლები\"  – ახალქალაქის ჰოსპიტალი",
              "AvailableCount": 12,
              "BranchAddress": "დ. აღმაშენებლის ქ N 31"
            }
          ],
          "AvailableCount": 12
        }
      ],
      "AvailableCount": 741
    }
  ],
  "Municipalities": [
    {
      "RegionId": "31520d88-870e-485e-a833-5ca9e20e84fa",
      "RegionName": "აჭარა",
      "Id": "057b6a5e-e0ae-41ed-99e5-a425a367f69b",
      "Name": "ბათუმი",
      "Locations": [
        {
          "BranchId": "1cc40657-dcdd-44fa-8f75-4f1a183febce",
          "BranchName": "შპს \"ბათუმის სამედიცინო ცენტრი\"",
          "AvailableCount": 536,
          "BranchAddress": "ბათუმი, კახაბერის ქ. N36"
        },
        {
          "BranchId": "26e2ab50-ed88-40b1-9b40-6d1d810dd958",
          "BranchName": "შპს მაღალტექნოლოგიური ჰოსპიტალი მედცენტრი",
          "AvailableCount": 395,
          "BranchAddress": "ქ.ბათუმი, პუშკინის ქ.N118/120"
        }
      ],
      "AvailableCount": 931
    },
    {
      "RegionId": "27428de4-bb76-47f2-bfac-26700623a05d",
      "RegionName": "გურია",
      "Id": "730cfadd-1b98-43ee-a908-81942b384b8b",
      "Name": "ოზურგეთი",
      "Locations": [
        {
          "BranchId": "b14d6cb5-9f46-4f80-a0a2-18ca4a282625",
          "BranchName": "შპს მედალფა_ოზურგეთი",
          "AvailableCount": 379,
          "BranchAddress": "ოზურგეთი, ე. ნინოშვილის ქ. №3 (იყო ჟღენტის ქ. №4) (თბილისი, ჯ. ბაგრატიონის ქ. №6ა)"
        }
      ],
      "AvailableCount": 379
    },
    {
      "RegionId": "5d129a50-30e9-4b10-8d4d-3febb32ec32c",
      "RegionName": "თბილისი",
      "Id": "e937c51e-2ed5-414e-b406-b9b1c59c6e29",
      "Name": "დიდუბე",
      "Locations": [
        {
          "BranchId": "d498c105-2c24-4217-8143-17ba88d01c39",
          "BranchName": "სს „ევექსის ჰოსპიტლები“ - მ. იაშვილის სახელობის ბავშვთა ცენტრალური საავადმყოფო",
          "AvailableCount": 824,
          "BranchAddress": "თბილისი, ლუბლიანას ქ. 13/მიხეილ ჭიაურელის ქ. 6 (ყოფ.: ლუბლიანას ქ. 2/6)"
        },
        {
          "BranchId": "89e3d6ec-fbe1-4673-95e1-74203d7f38e4",
          "BranchName": "შპს აკადემიკოს ო. ღუდუშაურის სახელობის ეროვნული სამედიცინო ცენტრი",
          "AvailableCount": 126,
          "BranchAddress": "თბილისი,ნოდარ ბოხუას ქ.N12/ლუბლიანას ქ.N66"
        },
        {
          "BranchId": "9f433fbf-df54-4d7d-a8df-2d653a249ee7",
          "BranchName": "ა(ა)იპ \"ნიუ ვიჟენ საუნივერსიტეტო ჰოსპიტალი\"",
          "AvailableCount": 370,
          "BranchAddress": "თბილისი, ლუბლიანას ქუჩა N13 / მიხეილ ჭიაურელის ქუჩა N6"
        }
      ],
      "AvailableCount": 1320
    },
    {
      "RegionId": "09c1e04c-c664-4252-a30a-2a71ba72c2e2",
      "RegionName": "იმერეთი",
      "Id": "f94b943e-a45a-4f51-8abc-479ba287be2f",
      "Name": "ბაღდათი",
      "Locations": [
        {
          "BranchId": "c8b86b01-7cd8-43b9-83cd-3eb75b183848",
          "BranchName": "შპს „ჯეო ჰოსპიტალს\" - ბაღდათის მრავალპროფილური სამედიცინო ცენტრი",
          "AvailableCount": 956,
          "BranchAddress": "ბაღდათი,\tკახიანის №84 (თბილისი კოსტავას 67, ბინა 71)"
        }
      ],
      "AvailableCount": 956
    },
    {
      "RegionId": "d1e285b5-5b60-42c6-9bc2-ac7646a9c96a",
      "RegionName": "კახეთი",
      "Id": "e77963c8-7b89-4662-8b70-92741c849e69",
      "Name": "გურჯაანი",
      "Locations": [
        {
          "BranchId": "d0376b52-af3e-44a7-ba20-208df006c981",
          "BranchName": "შპს „ჯეო ჰოსპიტალს\" - გურჯაანის მრავალპროფილური სამედიცინო ცენტრი",
          "AvailableCount": 192,
          "BranchAddress": "გურჯაანი, მარჯანიშვილის ქ. №35(იყო გურჯაანი, დ. აღმაშენებლის №144 (თბილისი კოსტავას 67, ბინა 71)"
        }
      ],
      "AvailableCount": 192
    },
    {
      "RegionId": "b5a01ce4-bbfc-4b7e-a519-ba11dd7146bb",
      "RegionName": "მცხეთა-მთიანეთი",
      "Id": "32f910b4-32be-4ee3-bde2-687f5c09db58",
      "Name": "დუშეთი",
      "Locations": [
        {
          "BranchId": "31f728e7-e6c2-487a-8068-6123d9f657ae",
          "BranchName": "შპს „ჯეო ჰოსპიტალს\" - დუშეთის მრავალპროფილური სამედიცინო ცენტრი",
          "AvailableCount": 319,
          "BranchAddress": "დუშეთი,\tსტალინის ქ. №71 (თბილისი კოსტავას 67, ბინა 71)"
        }
      ],
      "AvailableCount": 319
    },
    {
      "RegionId": "6d893d1f-3851-4d80-b7fc-020179c8a4c0",
      "RegionName": "რაჭა-ლეჩხუმი და ქვემო სვანეთი",
      "Id": "5aea027a-1970-4262-9c8b-85d804d049a2",
      "Name": "ამბროლაური",
      "Locations": [
        {
          "BranchId": "838c60c2-a8fe-4633-8aa1-28a7dde7afe1",
          "BranchName": "შპს \"რეგიონული ჯანდაცვის ცენტრი\"-ამბროლაური",
          "AvailableCount": 324,
          "BranchAddress": "ბრატისლავა-რაჭის11"
        }
      ],
      "AvailableCount": 324
    },
    {
      "RegionId": "a2a56af7-2f62-4ffa-aa56-038328bd5b32",
      "RegionName": "სამეგრელო და ზემო სვანეთი",
      "Id": "f736a3b3-c9cb-46b0-b18f-ee5627f6122a",
      "Name": "ზუგდიდი",
      "Locations": [
        {
          "BranchId": "54c76614-d1b1-47c1-9c12-f0415d1ac17c",
          "BranchName": "ნიკოლოზ ყიფშიძის სახელობის ცენტრალური საუნივერსიტეტო კლინიკა, ზუგდიდის რაიონი სოფელი რუხი",
          "AvailableCount": 167,
          "BranchAddress": "ზუგდიდი, სოფელი რუხი"
        },
        {
          "BranchId": "480edfc8-b97e-4db1-b4b7-262d35b63235",
          "BranchName": "სს \"ევექსის ჰოსპიტლები\" - ზუგდიდის რეფერალური ჰოსპიტალი",
          "AvailableCount": 359,
          "BranchAddress": "ზუგდიდი, გამსახურდიას ქ. # 206"
        }
      ],
      "AvailableCount": 526
    },
    {
      "RegionId": "acecd83d-fb22-44f9-b69d-3333aceb79a6",
      "RegionName": "სამცხე-ჯავახეთი",
      "Id": "c57a9137-d6bb-4247-a012-5e9b51558c89",
      "Name": "ახალქალაქი",
      "Locations": [
        {
          "BranchId": "869212c2-344d-45a3-8b53-311112b62839",
          "BranchName": "სს \"ევექსის ჰოსპიტლები\"  – ახალქალაქის ჰოსპიტალი",
          "AvailableCount": 377,
          "BranchAddress": "დ. აღმაშენებლის ქ N 31"
        }
      ],
      "AvailableCount": 377
    },
    {
      "RegionId": "f2cf4fc9-7037-4c56-8db7-bd9a6ddadd8a",
      "RegionName": "ქვემო ქართლი",
      "Id": "98a421a5-14d8-4cdd-bc99-5f70575c15ab",
      "Name": "გარდაბანი",
      "Locations": [
        {
          "BranchId": "71928d68-b24b-421d-9c44-69afacb65da8",
          "BranchName": "შპს „ჯეო ჰოსპიტალს\" - გარდაბნის მრავალპროფილური სამედიცინო ცენტრი",
          "AvailableCount": 346,
          "BranchAddress": "ქ. გარდაბანი, ლესელიძის ქ. N1(იყო დ.აღმაშენებლის №27 (თბილისი კოსტავას 67, ბინა 71)"
        }
      ],
      "AvailableCount": 346
    },
    {
      "RegionId": "ae3b6e33-6cd7-4b24-bf74-865cfabc2839",
      "RegionName": "შიდა ქართლი",
      "Id": "4561b508-0a64-4f59-b0f6-bf14e3e02fa4",
      "Name": "გორი",
      "Locations": [
        {
          "BranchId": "70ff295b-df28-4b41-a0d5-00a35e4b4762",
          "BranchName": "შპს გორმედი",
          "AvailableCount": 350,
          "BranchAddress": "გორი, ცხინვალის გზატკეცილი №14"
        },
        {
          "BranchId": "46843c12-6e0f-4d11-bca5-cfcad0d5edf8",
          "BranchName": "სსიპ გიორგი აბრამიშვილის სახელობის საქართველოს თავდაცვის სამინისტროს სამხედრო ჰოსპიტალი",
          "AvailableCount": 26,
          "BranchAddress": "გორი. ჭავჭავაძის N56"
        }
      ],
      "AvailableCount": 376
    }
  ],
  "LastUpdateDt": "2021-05-10T16:07:28.0750228+04:00"
}